RobotNotice.py
robotnotice-0.0.2.dist-info/LICENSE
robotnotice-0.0.2.dist-info/METADATA
robotnotice-0.0.2.dist-info/WHEEL
robotnotice-0.0.2.dist-info/top_level.txt
robotnotice-0.0.2.dist-info/RECORD
