Metadata-Version: 2.1
Name: robotnotice
Version: 0.0.2
Summary: 提供方便通用的钉钉群和企业微信群机器人消息通知接口
Home-page: https://github.com/yathon/RobotNotice
Author: Yathon
Author-email: Yathon <yathon@dyxt.com>
License: GNU General Public License v3 (GPLv3)
Project-URL: Homepage, https://github.com/yathon/RobotNotice
Project-URL: Bug Tracker, https://github.com/yathon/RobotNotice/issues/new
Classifier: Programming Language :: Python :: 3
Classifier: License :: OSI Approved :: GNU General Public License v3 (GPLv3)
Classifier: Operating System :: OS Independent
Requires-Python: >=3.7
License-File: LICENSE
Requires-Dist: asyncio
Requires-Dist: aiohttp
Requires-Dist: requests
